sheet_disk/__init__.py
sheet_disk/__version__.py
sheet_disk/cli.py
sheet_disk/my_logging.py
sheet_disk/sheet_classes.py
sheet_disk/sheet_disk.py
sheet_disk/utils.py
sheet_disk-0.1.1.dist-info/LICENSE
sheet_disk-0.1.1.dist-info/METADATA
sheet_disk-0.1.1.dist-info/WHEEL
sheet_disk-0.1.1.dist-info/top_level.txt
sheet_disk-0.1.1.dist-info/RECORD
