Metadata-Version: 2.1
Name: sheet-disk
Version: 0.1.1
Summary: Use Google Sheets as a storage device!
Home-page: https://github.com/vinay-deshmukh/Sheet-Disk
Author: Vinay Deshmukh
Author-email: vinay.deshmukh.official@outlook.com
License: UNKNOWN
Platform: UNKNOWN
Classifier: Programming Language :: Python :: 3 :: Only
Classifier: License :: OSI Approved :: MIT License
Classifier: Operating System :: OS Independent
Requires-Dist: gspread (>=3.0.1)
Requires-Dist: oauth2client (>=4.1.3)
